wielder/__init__.py
wielder/datastore_admin/__init__.py
wielder/datastore_admin/kafka_cli_conf.py
wielder/test/__init__.py
wielder/test/test_helmer.py
wielder/util/__init__.py
wielder/util/arguer.py
wielder/util/beautify.py
wielder/util/boto3_session_cache.py
wielder/util/bucketeer.py
wielder/util/commander.py
wielder/util/data_conf.py
wielder/util/hocon_util.py
wielder/util/hocon_wrapper.py
wielder/util/imager.py
wielder/util/log_util.py
wielder/util/plan.py
wielder/util/pod_logger.py
wielder/util/service_creator.py
wielder/util/templater.py
wielder/util/terraform_credential_helper.py
wielder/util/terraformer.py
wielder/util/util.py
wielder/util/wgit.py
wielder/wield/__init__.py
wielder/wield/base.py
wielder/wield/deployer.py
wielder/wield/enumerator.py
wielder/wield/helmer.py
wielder/wield/kube_probe.py
wielder/wield/modality.py
wielder/wield/planner.py
wielder/wield/servicer.py
wielder/wield/wield_project.py
wielder/wield/wield_service.py
wielder/wield/wielder_project_locale.py
wielder-0.2.7.dist-info/LICENSE
wielder-0.2.7.dist-info/LICENSE.txt
wielder-0.2.7.dist-info/METADATA
wielder-0.2.7.dist-info/WHEEL
wielder-0.2.7.dist-info/top_level.txt
wielder-0.2.7.dist-info/RECORD
