Metadata-Version: 2.1
Name: wielder
Version: 0.2.7
Summary: A reactive debuggable CI-CD & orchestration management tool for local & cloud deployments e.g. kubernetes, airflow & data lakes
Home-page: https://github.com/hamshif/Wielder.git
Author: Hamshif
Author-email: hamshif@gmail.com
License: Apache License Version 2.0
Download-URL: https://github.com/hamshif/Wielder/archive/v0.2.7-beta.tar.gz
Keywords: CI-CD,Kubernetes,Reactive
Platform: UNKNOWN
Classifier: Development Status :: 4 - Beta
Classifier: Intended Audience :: Developers
Classifier: Topic :: Software Development :: Build Tools
Classifier: License :: OSI Approved :: MIT License
Classifier: Programming Language :: Python :: 3
Classifier: Programming Language :: Python :: 3.7
Requires-Dist: Cython
Requires-Dist: gitpython
Requires-Dist: pyyaml
Requires-Dist: kubernetes
Requires-Dist: rx
Requires-Dist: jprops
Requires-Dist: pyhocon
Requires-Dist: requests
